supercalculator
