Metadata-Version: 2.1
Name: supercalculator
Version: 0.1.8
Summary: A high precision calculator
Home-page: 
Author: Raymond Grottodden
Author-email: raymondgrotto651@gmail.com
License: MIT
Keywords: calculator,precise,math
Classifier: Development Status :: 5 - Production/Stable
Classifier: Intended Audience :: Education
Classifier: Operating System :: Microsoft :: Windows :: Windows 10
Classifier: License :: OSI Approved :: MIT License
Classifier: Programming Language :: Python :: 3
License-File: LICENSE.txt
